[
    {
        "key": "dbln",
        "value": "%7B%2261564369751828%22%3A%22JfSZwBGw%22%2C%2261564285484995%22%3A%22rCyzTEue%22%7D",
        "domain": "facebook.com",
        "path": "/login/device-based/",
        "hostOnly": false,
        "creation": "2024-08-22T02:18:39.969Z",
        "lastAccessed": "2024-08-22T02:18:39.969Z"
    },
    {
        "key": "datr",
        "value": "HpTFZvyu7K761IOAo80b0PCu",
        "domain": "facebook.com",
        "path": "/",
        "hostOnly": false,
        "creation": "2024-08-22T02:18:39.969Z",
        "lastAccessed": "2024-08-22T02:18:39.969Z"
    },
    {
        "key": "sb",
        "value": "HpTFZsUM6106Dj24-c3v_gIi",
        "domain": "facebook.com",
        "path": "/",
        "hostOnly": false,
        "creation": "2024-08-22T02:18:39.969Z",
        "lastAccessed": "2024-08-22T02:18:39.969Z"
    },
    {
        "key": "vpd",
        "value": "v1%3B1036x501x1.4375",
        "domain": "facebook.com",
        "path": "/",
        "hostOnly": false,
        "creation": "2024-08-22T02:18:39.969Z",
        "lastAccessed": "2024-08-22T02:18:39.969Z"
    },
    {
        "key": "ps_l",
        "value": "1",
        "domain": "facebook.com",
        "path": "/",
        "hostOnly": false,
        "creation": "2024-08-22T02:18:39.969Z",
        "lastAccessed": "2024-08-22T02:18:39.969Z"
    },
    {
        "key": "ps_n",
        "value": "1",
        "domain": "facebook.com",
        "path": "/",
        "hostOnly": false,
        "creation": "2024-08-22T02:18:39.969Z",
        "lastAccessed": "2024-08-22T02:18:39.969Z"
    },
    {
        "key": "locale",
        "value": "en_GB",
        "domain": "facebook.com",
        "path": "/",
        "hostOnly": false,
        "creation": "2024-08-22T02:18:39.969Z",
        "lastAccessed": "2024-08-22T02:18:39.969Z"
    },
    {
        "key": "m_pixel_ratio",
        "value": "1.4375",
        "domain": "facebook.com",
        "path": "/",
        "hostOnly": false,
        "creation": "2024-08-22T02:18:39.969Z",
        "lastAccessed": "2024-08-22T02:18:39.969Z"
    },
    {
        "key": "wd",
        "value": "502x1036",
        "domain": "facebook.com",
        "path": "/",
        "hostOnly": false,
        "creation": "2024-08-22T02:18:39.969Z",
        "lastAccessed": "2024-08-22T02:18:39.969Z"
    },
    {
        "key": "c_user",
        "value": "61564285484995",
        "domain": "facebook.com",
        "path": "/",
        "hostOnly": false,
        "creation": "2024-08-22T02:18:39.969Z",
        "lastAccessed": "2024-08-22T02:18:39.969Z"
    },
    {
        "key": "fr",
        "value": "0SdFJ6jHHu1v7i6iX.AWUX_x807QJ9-6quO2-gks07xOA.BmxZQe..AAA.0.0.Bmxp_h.AWVllrllLYg",
        "domain": "facebook.com",
        "path": "/",
        "hostOnly": false,
        "creation": "2024-08-22T02:18:39.969Z",
        "lastAccessed": "2024-08-22T02:18:39.969Z"
    },
    {
        "key": "xs",
        "value": "20%3AAbDdfPV60CvCJQ%3A2%3A1724293089%3A-1%3A-1",
        "domain": "facebook.com",
        "path": "/",
        "hostOnly": false,
        "creation": "2024-08-22T02:18:39.969Z",
        "lastAccessed": "2024-08-22T02:18:39.969Z"
    },
    {
        "key": "m_page_voice",
        "value": "61564285484995",
        "domain": "facebook.com",
        "path": "/",
        "hostOnly": false,
        "creation": "2024-08-22T02:18:39.969Z",
        "lastAccessed": "2024-08-22T02:18:39.969Z"
    },
    {
        "key": "fbl_st",
        "value": "100438603%3BT%3A28738218",
        "domain": "facebook.com",
        "path": "/",
        "hostOnly": false,
        "creation": "2024-08-22T02:18:39.969Z",
        "lastAccessed": "2024-08-22T02:18:39.969Z"
    },
    {
        "key": "wl_cbv",
        "value": "v2%3Bclient_version%3A2599%3Btimestamp%3A1724293112",
        "domain": "facebook.com",
        "path": "/",
        "hostOnly": false,
        "creation": "2024-08-22T02:18:39.969Z",
        "lastAccessed": "2024-08-22T02:18:39.969Z"
    }
        ]
